sphinxcontrib_tryton-0.1.1-nspkg.pth
sphinxcontrib/tryton/__init__.py
sphinxcontrib/tryton/client.py
sphinxcontrib/tryton/client_sao.py
sphinxcontrib/tryton/client_tryton.py
sphinxcontrib/tryton/domain.py
sphinxcontrib/tryton/exception.py
sphinxcontrib/tryton/inherit.py
sphinxcontrib/tryton/trytond.py
test/__init__.py
test/test_builders.py
test/test_client_sao.py
test/test_client_tryton.py
test/test_domain.py
test/test_trytond.py
sphinxcontrib_tryton-0.1.1.dist-info/LICENSE
sphinxcontrib_tryton-0.1.1.dist-info/METADATA
sphinxcontrib_tryton-0.1.1.dist-info/WHEEL
sphinxcontrib_tryton-0.1.1.dist-info/namespace_packages.txt
sphinxcontrib_tryton-0.1.1.dist-info/top_level.txt
sphinxcontrib_tryton-0.1.1.dist-info/RECORD
