Metadata-Version: 2.1
Name: sphinxcontrib-tryton
Version: 0.1.1
Summary: A Sphinx extension that enables better documentation of Tryton.
Home-page: https://bitbucket.org/libateq/sphinxcontrib-tryton
Author: David Harper
Author-email: python-packages@libateq.org
License: GPL-3
Project-URL: Bug Tracker, https://bitbucket.org/libateq/sphinxcontrib-tryton/issues
Project-URL: Documentation, https://sphinxcontrib-tryton.readthedocs.org/
Project-URL: Source Code, https://bitbucket.org/libateq/sphinxcontrib-tryton
Keywords: sphinx tryton documentation
Platform: any
Classifier: Development Status :: 3 - Alpha
Classifier: Framework :: Sphinx :: Extension
Classifier: Intended Audience :: Developers
Classifier: Intended Audience :: System Administrators
Classifier: License :: OSI Approved :: GNU General Public License v3 or later (GPLv3+)
Classifier: Natural Language :: English
Classifier: Operating System :: OS Independent
Classifier: Programming Language :: Python :: 3
Classifier: Programming Language :: Python :: 3.5
Classifier: Programming Language :: Python :: 3.6
Classifier: Programming Language :: Python :: 3.7
Classifier: Programming Language :: Python :: 3.8
Classifier: Topic :: Documentation
Classifier: Topic :: Documentation :: Sphinx
Requires-Python: >=3.5
Requires-Dist: Sphinx (>=2.0.0)
Requires-Dist: proteus (>=5.0.0)
